MANIFEST.in
README.rst
setup.py
version
youtrack_scripts.egg-info/PKG-INFO
youtrack_scripts.egg-info/SOURCES.txt
youtrack_scripts.egg-info/dependency_links.txt
youtrack_scripts.egg-info/entry_points.txt
youtrack_scripts.egg-info/requires.txt
youtrack_scripts.egg-info/top_level.txt
youtrackutils/__init__.py
youtrackutils/bugzilla2youtrack.py
youtrackutils/csv2youtrack.py
youtrackutils/fb2youtrack.py
youtrackutils/github2youtrack.py
youtrackutils/mantis2youtrack.py
youtrackutils/moveIssue.py
youtrackutils/redmine2youtrack.py
youtrackutils/trac2youtrack.py
youtrackutils/userTool.py
youtrackutils/youtrack2youtrack.py
youtrackutils/zendesk2youtrack.py
youtrackutils/bugzilla/__init__.py
youtrackutils/bugzilla/bzClient.py
youtrackutils/bugzilla/defaultBzMapping.py
youtrackutils/csvClient/__init__.py
youtrackutils/csvClient/asanaMapping.py
youtrackutils/csvClient/client.py
youtrackutils/csvClient/youtrackMapping.py
youtrackutils/fbugz/__init__.py
youtrackutils/fbugz/defaultFBugz.py
youtrackutils/fbugz/fbSOAPClient.py
youtrackutils/fbugz/fogbugz.py
youtrackutils/mantis/__init__.py
youtrackutils/mantis/defaultMantis.py
youtrackutils/mantis/mantisClient.py
youtrackutils/redmine/__init__.py
youtrackutils/redmine/client.py
youtrackutils/redmine/mapping.py
youtrackutils/tracLib/__init__.py
youtrackutils/tracLib/client.py
youtrackutils/tracLib/defaultTrac.py
youtrackutils/tracLib/timetracking.py
youtrackutils/utils/__init__.py
youtrackutils/utils/mapfile.py
youtrackutils/zendesk/__init__.py
youtrackutils/zendesk/zendeskClient.py