Metadata-Version: 1.2
Name: youtrack-scripts
Version: 0.1.27
Summary: YouTrack import and utility scripts
Home-page: https://github.com/JetBrains/youtrack-python-scripts
Maintainer: Alexander Buturlinov
Maintainer-email: imboot85@gmail.com
License: Apache 2.0
Platform: UNKNOWN
Requires-Python: >=2.6, <3
